{
	"format_version": "1.12.0",
	"minecraft:geometry": [
		{
			"description": {
				"identifier": "geometry.unknown",
				"texture_width": 128,
				"texture_height": 128,
				"visible_bounds_width": 2,
				"visible_bounds_height": 3.5,
				"visible_bounds_offset": [0, 1.25, 0]
			},
			"bones": [
				{
					"name": "Ground",
					"pivot": [0, 0, 0]
				},
				{
					"name": "MainHead",
					"parent": "Ground",
					"pivot": [0, 16, 0],
					"cubes": [
						{"origin": [-8, 12, -8], "size": [16, 8, 16], "uv": [0, 0]},
						{"origin": [7.5, 7, -7.5], "size": [0, 5, 13], "pivot": [0, 16, 0], "rotation": [0, 0, -2.5], "uv": [64, 0]},
						{"origin": [-7.5, 7, -7.5], "size": [0, 5, 13], "pivot": [0, 16, 0], "rotation": [0, 0, 2.5], "uv": [64, 0]},
						{"origin": [-7.5, 7, -7.5], "size": [15, 5, 0], "pivot": [0, 16, 0], "rotation": [-2.5, 0, 0], "uv": [64, 34]},
						{"origin": [-8, 20, -8], "size": [16, 8, 16], "uv": [0, 24]}
					]
				},
				{
					"name": "Jaw",
					"parent": "MainHead",
					"pivot": [0, 12, 7],
					"cubes": [
						{"origin": [-7, 10, 5], "size": [14, 2, 2], "uv": [64, 18]},
						{"origin": [-7.5, 7, -7.5], "size": [15, 3, 15], "uv": [0, 48]},
						{"origin": [-7, 10, -7], "size": [14, 5, 12], "uv": [60, 48]}
					]
				},
				{
					"name": "Head",
					"parent": "MainHead",
					"pivot": [0, 20, 0],
					"cubes": [
						{"origin": [-3, 17, -3], "size": [6, 6, 6], "uv": [64, 22]}
					]
				}
			]
		}
	]
}